{
  "users": [
    {
      "id": 1,
      "name": "David Clark",
      "email": "d@fakeemail.com"
    },
    {
      "id": 2,
      "name": "Kelsey Keny",
      "email": "k@fakeemail.com"
    }
  ],
  "hunts": [
    {
      "id": 1,
      "title": "Test Hunt",
      "rewardText": "Congrats!",
      "userId": 1
    }
  ],
  "userHunts": [
    {
      "id": 1,
      "userId": 2,
      "huntId": 1,
      "stepsCompleted": 1
    }
  ],
  "clues": [
    {
      "id": 1,
      "clueText": "Test Hint",
      "clueAnswer": "Test Answer",
      "clueIndex": 1,
      "clueTypeId": 2,
      "huntId": 1
    }
  ],
  "clueTypes": [
    {
      "id": 1,
      "type": "Location"
    },
    {
      "id": 2,
      "type": "Item"
    }
  ]
}